surfacedocs/__init__.py
surfacedocs/client.py
surfacedocs/exceptions.py
surfacedocs/prompt.py
surfacedocs/schema.py
surfacedocs-0.1.0.dist-info/METADATA
surfacedocs-0.1.0.dist-info/WHEEL
surfacedocs-0.1.0.dist-info/licenses/LICENSE
surfacedocs-0.1.0.dist-info/RECORD
