Metadata-Version: 2.4
Name: surfacedocs
Version: 0.1.0
Summary: Python SDK for SurfaceDocs - Save LLM-generated documents
Project-URL: Homepage, https://surfacedocs.dev
Project-URL: Documentation, https://app.surfacedocs.dev/public/d/doc_VYMSDUFWvYBO
Author-email: SurfaceDocs <hello@surfacedocs.dev>, Sam Gallagher <gallaghersam95@gmail.com>
License-Expression: MIT
License-File: LICENSE
Keywords: ai,documentation,llm,sdk
Classifier: Development Status :: 3 - Alpha
Classifier: Intended Audience :: Developers
Classifier: License :: OSI Approved :: MIT License
Classifier: Programming Language :: Python :: 3
Classifier: Programming Language :: Python :: 3.9
Classifier: Programming Language :: Python :: 3.10
Classifier: Programming Language :: Python :: 3.11
Classifier: Programming Language :: Python :: 3.12
Requires-Python: >=3.9
Requires-Dist: httpx>=0.26.0
Provides-Extra: dev
Requires-Dist: build; extra == 'dev'
Requires-Dist: pytest-cov>=4.1.0; extra == 'dev'
Requires-Dist: pytest>=7.4.0; extra == 'dev'
Requires-Dist: respx>=0.20.0; extra == 'dev'
